zc_events/__init__.py
zc_events/aws.py
zc_events/client.py
zc_events/config.py
zc_events/django_request.py
zc_events/email.py
zc_events/event.py
zc_events/exceptions.py
zc_events/request.py
zc_events/responses.py
zc_events/routers.py
zc_events/tests.py
zc_events/utils.py
zc_events/backends/__init__.py
zc_events/backends/rabbitmqredis/__init__.py
zc_events/backends/rabbitmqredis/client.py
zc_events/backends/rabbitmqredis/common.py
zc_events/backends/rabbitmqredis/jsonapi.py
zc_events/backends/rabbitmqredis/server.py
zc_events/backends/rabbitmqredis/viewset_handler.py
zc_events/contrib/__init__.py
zc_events/contrib/email.py
zc_events-0.3.10.dist-info/METADATA
zc_events-0.3.10.dist-info/WHEEL
zc_events-0.3.10.dist-info/top_level.txt
zc_events-0.3.10.dist-info/RECORD
