Metadata-Version: 2.1
Name: zc-events
Version: 0.3.10
Summary: Shared code for ZeroCater microservices events
Home-page: https://github.com/ZeroCater/zc_events
Author: ZeroCater
Author-email: tech@zerocater.com
License: MIT
Download-URL: https://github.com/ZeroCater/zc_events/tarball/0.3.10
Keywords: zerocater python util
Platform: UNKNOWN
Classifier: License :: OSI Approved :: MIT License
Classifier: Programming Language :: Python
Classifier: Development Status :: 5 - Production/Stable
Classifier: Intended Audience :: Developers
Classifier: Topic :: Internet :: WWW/HTTP
Requires-Dist: boto3 (>=1.4.7)
Requires-Dist: celery (>=3.1.10)
Requires-Dist: inflection (<0.4,>=0.3.1)
Requires-Dist: pika (<0.11.0,>=0.10.0)
Requires-Dist: pika-pool (<0.1.4,>=0.1.3)
Requires-Dist: redis (<2.11.0,>=2.10.5)
Requires-Dist: ujson (<1.36,>=1.35)
Requires-Dist: zc-common (>=0.4.1)
Requires-Dist: pyjwt (<2.0.0,>=1.4.0)
Requires-Dist: six (>=1.10.0)
